metaflowbot/__init__.py
metaflowbot/actions/__init__.py
metaflowbot/actions/jokes/__init__.py
metaflowbot/actions/jokes/commands.py
metaflowbot/actions/jokes/rules.yml
metaflowbot_actions_jokes-1.0.1.dist-info/LICENSE
metaflowbot_actions_jokes-1.0.1.dist-info/METADATA
metaflowbot_actions_jokes-1.0.1.dist-info/WHEEL
metaflowbot_actions_jokes-1.0.1.dist-info/top_level.txt
metaflowbot_actions_jokes-1.0.1.dist-info/RECORD
