Metadata-Version: 2.1
Name: metaflowbot-actions-jokes
Version: 1.0.1
Summary: A Metaflow bot action for jokes
Home-page: UNKNOWN
Author: Valay Dave
Author-email: valaygaurang@gmail.com
License: Apache Software License 2.0
Platform: UNKNOWN
